psalm/__init__.py
psalm/core.py
pysalm-0.0.1.dist-info/LICENSE
pysalm-0.0.1.dist-info/METADATA
pysalm-0.0.1.dist-info/WHEEL
pysalm-0.0.1.dist-info/entry_points.txt
pysalm-0.0.1.dist-info/RECORD
